MANIFEST.in
README.rst
rapidpro-alert
rapidpro-backup-cleanup
rapidpro-change-role
rapidpro-change-status
rapidpro-cluster-available
rapidpro-cluster-check
rapidpro-cluster-ip
rapidpro-cluster-requestip
rapidpro-cluster-setipmaster
rapidpro-cluster-status
rapidpro-cluster-unavailable
rapidpro-config
rapidpro-configure-master
rapidpro-configure-slave
rapidpro-disable
rapidpro-dumpdb
rapidpro-enable
rapidpro-html-state
rapidpro-monit-reconfigure
rapidpro-notify-peer
rapidpro-peer-state
rapidpro-pgdump-to
rapidpro-postgres-status
rapidpro-receive-notif
rapidpro-record-failure
rapidpro-record-ipmaster
rapidpro-record-ipslave
rapidpro-restart
rapidpro-set-clustermode
rapidpro-set-role
rapidpro-set-status
rapidpro-start
rapidpro-state
rapidpro-status
rapidpro-stop
rapidpro-test-sms
setup.py
rapidpro_controller/__init__.py
rapidpro_controller/alerts.py
rapidpro_controller/cluster.py
rapidpro_controller/configuration.py
rapidpro_controller/dump.py
rapidpro_controller/postgres.py
rapidpro_controller/rapidproctl.conf.sample
rapidpro_controller/redis.py
rapidpro_controller/services.py
rapidpro_controller/sms.py
rapidpro_controller/states.py
rapidpro_controller/transitions.py
rapidpro_controller/xml2json.py
rapidpro_controller.egg-info/PKG-INFO
rapidpro_controller.egg-info/SOURCES.txt
rapidpro_controller.egg-info/dependency_links.txt
rapidpro_controller.egg-info/not-zip-safe
rapidpro_controller.egg-info/requires.txt
rapidpro_controller.egg-info/top_level.txt