Metadata-Version: 1.1
Name: rapidpro-controller
Version: 1.0
Summary: Management tools for RapidPro components
Home-page: http://github.com/rgaudin/rapidpro-controller
Author: renaud gaudin
Author-email: rgaudin@gmail.com
License: Public Domain
Keywords: rapidpro
Platform: any
Classifier: Development Status :: 4 - Beta
Classifier: Intended Audience :: Developers
Classifier: License :: Public Domain
Classifier: License :: CC0 1.0 Universal (CC0 1.0) Public Domain Dedication
Classifier: Programming Language :: Python
Classifier: Programming Language :: Python :: 2.7
